pyintellicenter/__init__.py
pyintellicenter/connection.py
pyintellicenter/controller.py
pyintellicenter/discovery.py
pyintellicenter/exceptions.py
pyintellicenter/model.py
pyintellicenter/types.py
pyintellicenter/attributes/__init__.py
pyintellicenter/attributes/body.py
pyintellicenter/attributes/circuit.py
pyintellicenter/attributes/constants.py
pyintellicenter/attributes/equipment.py
pyintellicenter/attributes/misc.py
pyintellicenter/attributes/schedule.py
pyintellicenter/attributes/system.py
pyintellicenter-0.1.14.dist-info/METADATA
pyintellicenter-0.1.14.dist-info/WHEEL
pyintellicenter-0.1.14.dist-info/licenses/LICENSE
pyintellicenter-0.1.14.dist-info/RECORD
