Metadata-Version: 2.4
Name: pyintellicenter
Version: 0.1.14
Summary: Python library for Pentair IntelliCenter pool control systems
Project-URL: Homepage, https://github.com/joyfulhouse/pyintellicenter
Project-URL: Documentation, https://github.com/joyfulhouse/pyintellicenter#readme
Project-URL: Repository, https://github.com/joyfulhouse/pyintellicenter.git
Project-URL: Issues, https://github.com/joyfulhouse/pyintellicenter/issues
Author-email: joyfulhouse <joyfulhouse@users.noreply.github.com>
License-Expression: MIT
License-File: LICENSE
Keywords: asyncio,automation,home-assistant,intellicenter,pentair,pool
Classifier: Development Status :: 4 - Beta
Classifier: Framework :: AsyncIO
Classifier: Intended Audience :: Developers
Classifier: License :: OSI Approved :: MIT License
Classifier: Operating System :: OS Independent
Classifier: Programming Language :: Python :: 3
Classifier: Programming Language :: Python :: 3.13
Classifier: Topic :: Home Automation
Classifier: Topic :: Software Development :: Libraries :: Python Modules
Classifier: Typing :: Typed
Requires-Python: >=3.13
Requires-Dist: orjson>=3.10.0
Requires-Dist: websockets>=15.0
Requires-Dist: zeroconf>=0.136.2
Provides-Extra: dev
Requires-Dist: mypy>=1.18.2; extra == 'dev'
Requires-Dist: pytest-asyncio>=1.3.0; extra == 'dev'
Requires-Dist: pytest-cov>=7.0.0; extra == 'dev'
Requires-Dist: pytest>=9.0.1; extra == 'dev'
Requires-Dist: ruff>=0.14.6; extra == 'dev'
